dboard/__init__.py
dboard/__main__.py
dboard/main.py
dboard/usecases/__init__.py
dboard/usecases/config.py
dboard/usecases/lib_rich.py
dboard-0.3.1.dist-info/LICENSE
dboard-0.3.1.dist-info/METADATA
dboard-0.3.1.dist-info/WHEEL
dboard-0.3.1.dist-info/top_level.txt
dboard-0.3.1.dist-info/RECORD
