Metadata-Version: 2.1
Name: dboard
Version: 0.3.1
Summary: A terminal dashboard
Author: Marcelo Félix
Requires-Python: >=3.8
License-File: LICENSE
Requires-Dist: pydantic
Requires-Dist: pyyaml
Requires-Dist: rich
